{
    "version": "4.5.4",
    "flags": {},
    "shapes": [
        {
            "label": "zone",
            "points": [
                [
                    74.41935483870968,
                    212.8709677419355
                ],
                [
                    759.9032258064516,
                    146.74193548387098
                ],
                [
                    1241.3548387096773,
                    293.51612903225805
                ],
                [
                    534.0967741935484,
                    686.258064516129
                ]
            ],
            "group_id": null,
            "shape_type": "polygon",
            "flags": {}
        },
        {
            "label": "direction01",
            "points": [
                [
                    336.51612903225805,
                    173.3548387096774
                ],
                [
                    1149.4193548387098,
                    515.2903225806451
                ]
            ],
            "group_id": null,
            "shape_type": "line",
            "flags": {}
        },
        {
            "label": "direction02",
            "points": [
                [
                    1230.0645161290322,
                    380.61290322580646
                ],
                [
                    498.61290322580646,
                    147.5483870967742
                ]
            ],
            "group_id": null,
            "shape_type": "line",
            "flags": {}
        },
        {
            "label": "direction03",
            "points": [
                [
                    1226.8387096774193,
                    396.741935483871
                ],
                [
                    51.03225806451613,
                    384.64516129032256
                ]
            ],
            "group_id": null,
            "shape_type": "line",
            "flags": {}
        },
        {
            "label": "direction04",
            "points": [
                [
                    356.6774193548387,
                    170.1290322580645
                ],
                [
                    62.322580645161295,
                    405.61290322580646
                ]
            ],
            "group_id": null,
            "shape_type": "line",
            "flags": {}
        },
        {
            "label": "direction05",
            "points": [
                [
                    121.19354838709677,
                    424.16129032258067
                ],
                [
                    485.7096774193548,
                    151.58064516129033
                ]
            ],
            "group_id": null,
            "shape_type": "line",
            "flags": {}
        },
        {
            "label": "direction06",
            "points": [
                [
                    127.64516129032259,
                    438.6774193548387
                ],
                [
                    1184.9032258064517,
                    448.35483870967744
                ]
            ],
            "group_id": null,
            "shape_type": "line",
            "flags": {}
        }
    ],
    "imagePath": "cam_20.png",
    "imageData": null,
    "imageHeight": 720,
    "imageWidth": 1280
}